ycache/__init__.py
ycache/core.py
ycache-0.3.1.dist-info/METADATA
ycache-0.3.1.dist-info/WHEEL
ycache-0.3.1.dist-info/RECORD
