Metadata-Version: 2.3
Name: ycache
Version: 0.3.1
Summary: a simple cache tools
Author: yapex
Author-email: yapex.yin@gmail.com
Requires-Python: >=3.13
Classifier: Programming Language :: Python :: 3
Classifier: Programming Language :: Python :: 3.13
Requires-Dist: diskcache (>=5.6.3,<6.0.0)
Requires-Dist: loguru (>=0.7.3,<0.8.0)
Requires-Dist: orjson (>=3.10.15,<4.0.0)
Requires-Dist: xxhash (>=3.5.0,<4.0.0)
